{
  "create_time": "2024-10-28 15.14.00",
  "awemeType": 1,
  "aweme_id": "7430690543375568167",
  "author": {
    "avatar_thumb": {
      "height": 720,
      "uri": "100x100/aweme-avatar/tos-cn-i-0813c001_o0AAil9AQiI7DwmrvZBQIjP3hPyuAvLnAi5EO",
      "url_list": [
        "https://p3-pc.douyinpic.com/aweme/100x100/aweme-avatar/tos-cn-i-0813c001_o0AAil9AQiI7DwmrvZBQIjP3hPyuAvLnAi5EO.jpeg?from=327834062"
      ],
      "width": 720
    },
    "avatar": {
      "height": 720,
      "uri": "1080x1080/aweme-avatar/tos-cn-i-0813c001_o0AAil9AQiI7DwmrvZBQIjP3hPyuAvLnAi5EO",
      "url_list": [
        "https://p3-pc.douyinpic.com/aweme/1080x1080/aweme-avatar/tos-cn-i-0813c001_o0AAil9AQiI7DwmrvZBQIjP3hPyuAvLnAi5EO.jpeg?from=327834062"
      ],
      "width": 720
    },
    "cover_url": {
      "height": 720,
      "uri": "c8510002be9a3a61aad2",
      "url_list": [
        "https://p3-pc-sign.douyinpic.com/obj/c8510002be9a3a61aad2?lk3s=138a59ce&x-expires=1743318000&x-signature=Mtg%2BXU4VTNyy1Y8efX75BRo3vHc%3D&from=327834062",
        "https://p9-pc-sign.douyinpic.com/obj/c8510002be9a3a61aad2?lk3s=138a59ce&x-expires=1743318000&x-signature=qOViAiZuSDSZDWIesivpJq3FTFA%3D&from=327834062"
      ],
      "width": 720
    },
    "favoriting_count": "",
    "follower_count": "",
    "following_count": "",
    "nickname": "仙女🧚‍♀️头像",
    "prevent_download": false,
    "sec_uid": "MS4wLjABAAAARxfYGr6sQd6eyCtqy3_sGUK2M4AGlLlrSPoCHc3c0gk",
    "secret": "",
    "short_id": "",
    "signature": "",
    "total_favorited": "",
    "uid": "237952352129216",
    "unique_id": "",
    "user_age": ""
  },
  "desc": "天啊❗️什么神仙壁纸也太美了吧～🤩🤩。#纯欲天花板 #氛围感美女 #手机壁纸",
  "images": [
    {
      "height": 2560,
      "mask_url_list": null,
      "uri": "tos-cn-i-0813c001/oYfWAPMAAQOAXAftta8E7ePEamcdHjBFAQBuRI",
      "url_list": [
        "https://p3-pc-sign.douyinpic.com/tos-cn-i-0813c001/oYfWAPMAAQOAXAftta8E7ePEamcdHjBFAQBuRI~tplv-dy-aweme-images:q75.webp?lk3s=138a59ce&x-expires=1744700400&x-signature=CNfrLRWa7km%2FaHWQVXIYdbwQdQo%3D&from=327834062&s=PackSourceEnum_PUBLISH&se=false&sc=image&biz_tag=aweme_images&l=2025031615434800233C9A7B773538C172",
        "https://p9-pc-sign.douyinpic.com/tos-cn-i-0813c001/oYfWAPMAAQOAXAftta8E7ePEamcdHjBFAQBuRI~tplv-dy-aweme-images:q75.webp?lk3s=138a59ce&x-expires=1744700400&x-signature=bYnjoDEzzT1NEDRGVK1OnmOofAg%3D&from=327834062&s=PackSourceEnum_PUBLISH&se=false&sc=image&biz_tag=aweme_images&l=2025031615434800233C9A7B773538C172",
        "https://p3-pc-sign.douyinpic.com/tos-cn-i-0813c001/oYfWAPMAAQOAXAftta8E7ePEamcdHjBFAQBuRI~tplv-dy-aweme-images:q75.jpeg?lk3s=138a59ce&x-expires=1744700400&x-signature=wf4hwZK8tG5fwk7SKtD%2BAg2RFJU%3D&from=327834062&s=PackSourceEnum_PUBLISH&se=false&sc=image&biz_tag=aweme_images&l=2025031615434800233C9A7B773538C172"
      ],
      "width": 1440,
      "download_url_list": [
        "https://p3-pc-sign.douyinpic.com/tos-cn-i-0813c001/oYfWAPMAAQOAXAftta8E7ePEamcdHjBFAQBuRI~tplv-dy-water-v2:5oqW6Z-z5Y-377yaNTg3OTgwOTYzMzU=:1440:2560.webp?lk3s=138a59ce&x-expires=1744700400&x-signature=5i4xJZ3NYabieU4L4VyDXeePvcE%3D&sig=e2Ov2wnoAAw38E3U5ZhNBomI9SU%3D&from=327834062&s=PackSourceEnum_PUBLISH&se=false&sc=image&biz_tag=aweme_images&l=2025031615434800233C9A7B773538C172",
        "https://p9-pc-sign.douyinpic.com/tos-cn-i-0813c001/oYfWAPMAAQOAXAftta8E7ePEamcdHjBFAQBuRI~tplv-dy-water-v2:5oqW6Z-z5Y-377yaNTg3OTgwOTYzMzU=:1440:2560.webp?lk3s=138a59ce&x-expires=1744700400&x-signature=Mj5A5ZKoebFz1Dlxqq%2FI8UvdB%2Fg%3D&sig=e2Ov2wnoAAw38E3U5ZhNBomI9SU%3D&from=327834062&s=PackSourceEnum_PUBLISH&se=false&sc=image&biz_tag=aweme_images&l=2025031615434800233C9A7B773538C172",
        "https://p3-pc-sign.douyinpic.com/tos-cn-i-0813c001/oYfWAPMAAQOAXAftta8E7ePEamcdHjBFAQBuRI~tplv-dy-water-v2:5oqW6Z-z5Y-377yaNTg3OTgwOTYzMzU=:1440:2560.jpeg?lk3s=138a59ce&x-expires=1744700400&x-signature=Ecaf6ximgZaAn5ZiTTTIEWQWAbg%3D&sig=70VkHtqeSvM9_C7amt8Uwhlhans%3D&from=327834062&s=PackSourceEnum_PUBLISH&se=false&sc=image&biz_tag=aweme_images&l=2025031615434800233C9A7B773538C172"
      ],
      "interaction_stickers": null
    },
    {
      "height": 2560,
      "mask_url_list": null,
      "uri": "tos-cn-i-0813c001/oEAQFHfaIemBaQPEcfcM8Bs7tPAXAAjAA7QOQW",
      "url_list": [
        "https://p3-pc-sign.douyinpic.com/tos-cn-i-0813c001/oEAQFHfaIemBaQPEcfcM8Bs7tPAXAAjAA7QOQW~tplv-dy-aweme-images:q75.webp?lk3s=138a59ce&x-expires=1744700400&x-signature=srpGWgbgHkuhjdUyJVWaze9W3dU%3D&from=327834062&s=PackSourceEnum_PUBLISH&se=false&sc=image&biz_tag=aweme_images&l=2025031615434800233C9A7B773538C172",
        "https://p9-pc-sign.douyinpic.com/tos-cn-i-0813c001/oEAQFHfaIemBaQPEcfcM8Bs7tPAXAAjAA7QOQW~tplv-dy-aweme-images:q75.webp?lk3s=138a59ce&x-expires=1744700400&x-signature=%2B%2Bj2Qj8%2FHSs3QU7SKF5UicI05C4%3D&from=327834062&s=PackSourceEnum_PUBLISH&se=false&sc=image&biz_tag=aweme_images&l=2025031615434800233C9A7B773538C172",
        "https://p3-pc-sign.douyinpic.com/tos-cn-i-0813c001/oEAQFHfaIemBaQPEcfcM8Bs7tPAXAAjAA7QOQW~tplv-dy-aweme-images:q75.jpeg?lk3s=138a59ce&x-expires=1744700400&x-signature=k4rRBU9MF0Y%2Bp%2Fjf3LuxN95BgG0%3D&from=327834062&s=PackSourceEnum_PUBLISH&se=false&sc=image&biz_tag=aweme_images&l=2025031615434800233C9A7B773538C172"
      ],
      "width": 1440,
      "download_url_list": [
        "https://p3-pc-sign.douyinpic.com/tos-cn-i-0813c001/oEAQFHfaIemBaQPEcfcM8Bs7tPAXAAjAA7QOQW~tplv-dy-water-v2:5oqW6Z-z5Y-377yaNTg3OTgwOTYzMzU=:1440:2560.webp?lk3s=138a59ce&x-expires=1744700400&x-signature=yLDysKDcMUiYOjRN5i96FSdKjDU%3D&sig=Hvy6Gn1Tf5MQ7utiid8SgJlcBQ0%3D&from=327834062&s=PackSourceEnum_PUBLISH&se=false&sc=image&biz_tag=aweme_images&l=2025031615434800233C9A7B773538C172",
        "https://p9-pc-sign.douyinpic.com/tos-cn-i-0813c001/oEAQFHfaIemBaQPEcfcM8Bs7tPAXAAjAA7QOQW~tplv-dy-water-v2:5oqW6Z-z5Y-377yaNTg3OTgwOTYzMzU=:1440:2560.webp?lk3s=138a59ce&x-expires=1744700400&x-signature=N8ydcFvG%2FxqiKbDttVpwFkm1%2FUA%3D&sig=Hvy6Gn1Tf5MQ7utiid8SgJlcBQ0%3D&from=327834062&s=PackSourceEnum_PUBLISH&se=false&sc=image&biz_tag=aweme_images&l=2025031615434800233C9A7B773538C172",
        "https://p3-pc-sign.douyinpic.com/tos-cn-i-0813c001/oEAQFHfaIemBaQPEcfcM8Bs7tPAXAAjAA7QOQW~tplv-dy-water-v2:5oqW6Z-z5Y-377yaNTg3OTgwOTYzMzU=:1440:2560.jpeg?lk3s=138a59ce&x-expires=1744700400&x-signature=Jva%2FUL%2FX7AigxNk74F8T3JDYNJc%3D&sig=92CkLJcN1-RKun5qhgggxhSNQ8k%3D&from=327834062&s=PackSourceEnum_PUBLISH&se=false&sc=image&biz_tag=aweme_images&l=2025031615434800233C9A7B773538C172"
      ],
      "interaction_stickers": null
    },
    {
      "height": 2564,
      "mask_url_list": null,
      "uri": "tos-cn-i-0813/oMcWBF8MaImQ7fOBeH2qAPcjfEaAKQtAXAAPQA",
      "url_list": [
        "https://p3-pc-sign.douyinpic.com/tos-cn-i-0813/oMcWBF8MaImQ7fOBeH2qAPcjfEaAKQtAXAAPQA~tplv-dy-aweme-images:q75.webp?lk3s=138a59ce&x-expires=1744700400&x-signature=2MxbIpCctcNNuYyM45%2FfW9twjGk%3D&from=327834062&s=PackSourceEnum_PUBLISH&se=false&sc=image&biz_tag=aweme_images&l=2025031615434800233C9A7B773538C172",
        "https://p9-pc-sign.douyinpic.com/tos-cn-i-0813/oMcWBF8MaImQ7fOBeH2qAPcjfEaAKQtAXAAPQA~tplv-dy-aweme-images:q75.webp?lk3s=138a59ce&x-expires=1744700400&x-signature=1GdCMeCQzwp6DkwzgtRk0ubuOfE%3D&from=327834062&s=PackSourceEnum_PUBLISH&se=false&sc=image&biz_tag=aweme_images&l=2025031615434800233C9A7B773538C172",
        "https://p3-pc-sign.douyinpic.com/tos-cn-i-0813/oMcWBF8MaImQ7fOBeH2qAPcjfEaAKQtAXAAPQA~tplv-dy-aweme-images:q75.jpeg?lk3s=138a59ce&x-expires=1744700400&x-signature=MdZhwTfoxSQdBfAbfvPqHXEJPvg%3D&from=327834062&s=PackSourceEnum_PUBLISH&se=false&sc=image&biz_tag=aweme_images&l=2025031615434800233C9A7B773538C172"
      ],
      "width": 1440,
      "download_url_list": [
        "https://p3-pc-sign.douyinpic.com/tos-cn-i-0813/oMcWBF8MaImQ7fOBeH2qAPcjfEaAKQtAXAAPQA~tplv-dy-water-v2:5oqW6Z-z5Y-377yaNTg3OTgwOTYzMzU=:1440:2564.webp?lk3s=138a59ce&x-expires=1744700400&x-signature=vAaxDxtR7pXEadEWpxua0llKMgc%3D&sig=CVSQ45sMkH0IhlLSsWb2Xlercho%3D&from=327834062&s=PackSourceEnum_PUBLISH&se=false&sc=image&biz_tag=aweme_images&l=2025031615434800233C9A7B773538C172",
        "https://p9-pc-sign.douyinpic.com/tos-cn-i-0813/oMcWBF8MaImQ7fOBeH2qAPcjfEaAKQtAXAAPQA~tplv-dy-water-v2:5oqW6Z-z5Y-377yaNTg3OTgwOTYzMzU=:1440:2564.webp?lk3s=138a59ce&x-expires=1744700400&x-signature=JlxozfvYM2nGtWGULgalH2GpcGA%3D&sig=CVSQ45sMkH0IhlLSsWb2Xlercho%3D&from=327834062&s=PackSourceEnum_PUBLISH&se=false&sc=image&biz_tag=aweme_images&l=2025031615434800233C9A7B773538C172",
        "https://p3-pc-sign.douyinpic.com/tos-cn-i-0813/oMcWBF8MaImQ7fOBeH2qAPcjfEaAKQtAXAAPQA~tplv-dy-water-v2:5oqW6Z-z5Y-377yaNTg3OTgwOTYzMzU=:1440:2564.jpeg?lk3s=138a59ce&x-expires=1744700400&x-signature=eryklnZeB2nXia37ZaIlRZLhr4k%3D&sig=SIW3pBcQXpQ8uRChiKPxT1Aqn2A%3D&from=327834062&s=PackSourceEnum_PUBLISH&se=false&sc=image&biz_tag=aweme_images&l=2025031615434800233C9A7B773538C172"
      ],
      "interaction_stickers": null
    },
    {
      "height": 2564,
      "mask_url_list": null,
      "uri": "tos-cn-i-0813c001/oUOAIfcBAMQcfAAAoHnE8XamtBa3PQWe7jPFYA",
      "url_list": [
        "https://p3-pc-sign.douyinpic.com/tos-cn-i-0813c001/oUOAIfcBAMQcfAAAoHnE8XamtBa3PQWe7jPFYA~tplv-dy-aweme-images:q75.webp?lk3s=138a59ce&x-expires=1744700400&x-signature=X6F1MWRe7kltjgMJmK1W355sUYw%3D&from=327834062&s=PackSourceEnum_PUBLISH&se=false&sc=image&biz_tag=aweme_images&l=2025031615434800233C9A7B773538C172",
        "https://p9-pc-sign.douyinpic.com/tos-cn-i-0813c001/oUOAIfcBAMQcfAAAoHnE8XamtBa3PQWe7jPFYA~tplv-dy-aweme-images:q75.webp?lk3s=138a59ce&x-expires=1744700400&x-signature=hY%2Fgsr%2BfOlVVXfVO9x4G05xp9zU%3D&from=327834062&s=PackSourceEnum_PUBLISH&se=false&sc=image&biz_tag=aweme_images&l=2025031615434800233C9A7B773538C172",
        "https://p3-pc-sign.douyinpic.com/tos-cn-i-0813c001/oUOAIfcBAMQcfAAAoHnE8XamtBa3PQWe7jPFYA~tplv-dy-aweme-images:q75.jpeg?lk3s=138a59ce&x-expires=1744700400&x-signature=chGljJyjqCRflvYBAIbjvDZtn2c%3D&from=327834062&s=PackSourceEnum_PUBLISH&se=false&sc=image&biz_tag=aweme_images&l=2025031615434800233C9A7B773538C172"
      ],
      "width": 1440,
      "download_url_list": [
        "https://p3-pc-sign.douyinpic.com/tos-cn-i-0813c001/oUOAIfcBAMQcfAAAoHnE8XamtBa3PQWe7jPFYA~tplv-dy-water-v2:5oqW6Z-z5Y-377yaNTg3OTgwOTYzMzU=:1440:2564.webp?lk3s=138a59ce&x-expires=1744700400&x-signature=T7T4ISjY%2F3htxbt%2FOh6cQb6mwhQ%3D&sig=oS6xyLZckTJ1WGZYj160-O71u7I%3D&from=327834062&s=PackSourceEnum_PUBLISH&se=false&sc=image&biz_tag=aweme_images&l=2025031615434800233C9A7B773538C172",
        "https://p9-pc-sign.douyinpic.com/tos-cn-i-0813c001/oUOAIfcBAMQcfAAAoHnE8XamtBa3PQWe7jPFYA~tplv-dy-water-v2:5oqW6Z-z5Y-377yaNTg3OTgwOTYzMzU=:1440:2564.webp?lk3s=138a59ce&x-expires=1744700400&x-signature=Yd6%2FTgVrGzVZiZsFDUsPqpkOCeY%3D&sig=oS6xyLZckTJ1WGZYj160-O71u7I%3D&from=327834062&s=PackSourceEnum_PUBLISH&se=false&sc=image&biz_tag=aweme_images&l=2025031615434800233C9A7B773538C172",
        "https://p3-pc-sign.douyinpic.com/tos-cn-i-0813c001/oUOAIfcBAMQcfAAAoHnE8XamtBa3PQWe7jPFYA~tplv-dy-water-v2:5oqW6Z-z5Y-377yaNTg3OTgwOTYzMzU=:1440:2564.jpeg?lk3s=138a59ce&x-expires=1744700400&x-signature=oGZEt2XXsAnvx%2B0Ph6680m4vAw8%3D&sig=PNxPwJL9N_bXLW5En4GIbj9IWoY%3D&from=327834062&s=PackSourceEnum_PUBLISH&se=false&sc=image&biz_tag=aweme_images&l=2025031615434800233C9A7B773538C172"
      ],
      "interaction_stickers": null
    },
    {
      "height": 2560,
      "mask_url_list": null,
      "uri": "tos-cn-i-0813/oEBBt0MeXA5PPOeAA7JMAEeB8mLQgaA8AOjsJQ",
      "url_list": [
        "https://p3-pc-sign.douyinpic.com/tos-cn-i-0813/oEBBt0MeXA5PPOeAA7JMAEeB8mLQgaA8AOjsJQ~tplv-dy-aweme-images:q75.webp?lk3s=138a59ce&x-expires=1744700400&x-signature=X%2Fa%2B40rJCWGcRvZjN43V1OpqQjo%3D&from=327834062&s=PackSourceEnum_PUBLISH&se=false&sc=image&biz_tag=aweme_images&l=2025031615434800233C9A7B773538C172",
        "https://p9-pc-sign.douyinpic.com/tos-cn-i-0813/oEBBt0MeXA5PPOeAA7JMAEeB8mLQgaA8AOjsJQ~tplv-dy-aweme-images:q75.webp?lk3s=138a59ce&x-expires=1744700400&x-signature=x9e7HnPDC%2Bwqex6RZipRop0Y%2By4%3D&from=327834062&s=PackSourceEnum_PUBLISH&se=false&sc=image&biz_tag=aweme_images&l=2025031615434800233C9A7B773538C172",
        "https://p3-pc-sign.douyinpic.com/tos-cn-i-0813/oEBBt0MeXA5PPOeAA7JMAEeB8mLQgaA8AOjsJQ~tplv-dy-aweme-images:q75.jpeg?lk3s=138a59ce&x-expires=1744700400&x-signature=RRdPuZdCOMvRFTIzoPCLeWtu1oA%3D&from=327834062&s=PackSourceEnum_PUBLISH&se=false&sc=image&biz_tag=aweme_images&l=2025031615434800233C9A7B773538C172"
      ],
      "width": 1440,
      "download_url_list": [
        "https://p3-pc-sign.douyinpic.com/tos-cn-i-0813/oEBBt0MeXA5PPOeAA7JMAEeB8mLQgaA8AOjsJQ~tplv-dy-water-v2:5oqW6Z-z5Y-377yaNTg3OTgwOTYzMzU=:1440:2560.webp?lk3s=138a59ce&x-expires=1744700400&x-signature=NfF5W8l27%2BPm%2FAfKpt%2Fz8p8nNlQ%3D&sig=y0Bt3SQm98y2gF0GdFmDDdRZAdA%3D&from=327834062&s=PackSourceEnum_PUBLISH&se=false&sc=image&biz_tag=aweme_images&l=2025031615434800233C9A7B773538C172",
        "https://p9-pc-sign.douyinpic.com/tos-cn-i-0813/oEBBt0MeXA5PPOeAA7JMAEeB8mLQgaA8AOjsJQ~tplv-dy-water-v2:5oqW6Z-z5Y-377yaNTg3OTgwOTYzMzU=:1440:2560.webp?lk3s=138a59ce&x-expires=1744700400&x-signature=34L%2FrBCHezIBj90nSJ%2BmRfMjM4g%3D&sig=y0Bt3SQm98y2gF0GdFmDDdRZAdA%3D&from=327834062&s=PackSourceEnum_PUBLISH&se=false&sc=image&biz_tag=aweme_images&l=2025031615434800233C9A7B773538C172",
        "https://p3-pc-sign.douyinpic.com/tos-cn-i-0813/oEBBt0MeXA5PPOeAA7JMAEeB8mLQgaA8AOjsJQ~tplv-dy-water-v2:5oqW6Z-z5Y-377yaNTg3OTgwOTYzMzU=:1440:2560.jpeg?lk3s=138a59ce&x-expires=1744700400&x-signature=zgx1IU8Iki9BzpF4U6Kb9Q3iJ2Y%3D&sig=Mq8NK_6oe97nKKXMAEoeTWUz-0Y%3D&from=327834062&s=PackSourceEnum_PUBLISH&se=false&sc=image&biz_tag=aweme_images&l=2025031615434800233C9A7B773538C172"
      ],
      "interaction_stickers": null
    },
    {
      "height": 2564,
      "mask_url_list": null,
      "uri": "tos-cn-i-0813/oQ5eP8tQAs7LAgeQNEXOAOBMAIabABi08jPBem",
      "url_list": [
        "https://p3-pc-sign.douyinpic.com/tos-cn-i-0813/oQ5eP8tQAs7LAgeQNEXOAOBMAIabABi08jPBem~tplv-dy-aweme-images:q75.webp?lk3s=138a59ce&x-expires=1744700400&x-signature=Y2vVDA1FmRd0ZXfvqU%2FjgH%2BAFGc%3D&from=327834062&s=PackSourceEnum_PUBLISH&se=false&sc=image&biz_tag=aweme_images&l=2025031615434800233C9A7B773538C172",
        "https://p9-pc-sign.douyinpic.com/tos-cn-i-0813/oQ5eP8tQAs7LAgeQNEXOAOBMAIabABi08jPBem~tplv-dy-aweme-images:q75.webp?lk3s=138a59ce&x-expires=1744700400&x-signature=h6FQggcsC6MOb26X%2BbvR8kqqTS8%3D&from=327834062&s=PackSourceEnum_PUBLISH&se=false&sc=image&biz_tag=aweme_images&l=2025031615434800233C9A7B773538C172",
        "https://p3-pc-sign.douyinpic.com/tos-cn-i-0813/oQ5eP8tQAs7LAgeQNEXOAOBMAIabABi08jPBem~tplv-dy-aweme-images:q75.jpeg?lk3s=138a59ce&x-expires=1744700400&x-signature=9R8wxzWP%2FXopUlGzU5JzGBDnBEQ%3D&from=327834062&s=PackSourceEnum_PUBLISH&se=false&sc=image&biz_tag=aweme_images&l=2025031615434800233C9A7B773538C172"
      ],
      "width": 1440,
      "download_url_list": [
        "https://p9-pc-sign.douyinpic.com/tos-cn-i-0813/oQ5eP8tQAs7LAgeQNEXOAOBMAIabABi08jPBem~tplv-dy-water-v2:5oqW6Z-z5Y-377yaNTg3OTgwOTYzMzU=:1440:2564.webp?lk3s=138a59ce&x-expires=1744700400&x-signature=8aRMF9wHAYwQAbr0%2BV5NCcB4wgI%3D&sig=TiftlgwoiF50vdU9t6mApNYKmvU%3D&from=327834062&s=PackSourceEnum_PUBLISH&se=false&sc=image&biz_tag=aweme_images&l=2025031615434800233C9A7B773538C172",
        "https://p3-pc-sign.douyinpic.com/tos-cn-i-0813/oQ5eP8tQAs7LAgeQNEXOAOBMAIabABi08jPBem~tplv-dy-water-v2:5oqW6Z-z5Y-377yaNTg3OTgwOTYzMzU=:1440:2564.webp?lk3s=138a59ce&x-expires=1744700400&x-signature=VPqyNLI%2BdRBdjskGrNgQ5iC6uac%3D&sig=TiftlgwoiF50vdU9t6mApNYKmvU%3D&from=327834062&s=PackSourceEnum_PUBLISH&se=false&sc=image&biz_tag=aweme_images&l=2025031615434800233C9A7B773538C172",
        "https://p9-pc-sign.douyinpic.com/tos-cn-i-0813/oQ5eP8tQAs7LAgeQNEXOAOBMAIabABi08jPBem~tplv-dy-water-v2:5oqW6Z-z5Y-377yaNTg3OTgwOTYzMzU=:1440:2564.jpeg?lk3s=138a59ce&x-expires=1744700400&x-signature=ezHFS1lZky1lMjVDVr%2FVKMDFCmE%3D&sig=YDV_EDGGNodgnWzPJ5Ky5GKSUAQ%3D&from=327834062&s=PackSourceEnum_PUBLISH&se=false&sc=image&biz_tag=aweme_images&l=2025031615434800233C9A7B773538C172"
      ],
      "interaction_stickers": null
    }
  ],
  "music": {
    "cover_hd": {
      "height": 720,
      "uri": "tos-cn-v-2774c002/okWaEAQZAt0QADBJBAgiQ5PVEfBimeiBNATwlC",
      "url_list": [
        "https://p11.douyinpic.com/aweme/1080x1080/tos-cn-v-2774c002/okWaEAQZAt0QADBJBAgiQ5PVEfBimeiBNATwlC.jpeg",
        "https://p26.douyinpic.com/aweme/1080x1080/tos-cn-v-2774c002/okWaEAQZAt0QADBJBAgiQ5PVEfBimeiBNATwlC.jpeg"
      ],
      "width": 720
    },
    "cover_large": {
      "height": 720,
      "uri": "tos-cn-v-2774c002/okWaEAQZAt0QADBJBAgiQ5PVEfBimeiBNATwlC",
      "url_list": [
        "https://p11.douyinpic.com/aweme/720x720/tos-cn-v-2774c002/okWaEAQZAt0QADBJBAgiQ5PVEfBimeiBNATwlC.jpeg",
        "https://p26.douyinpic.com/aweme/720x720/tos-cn-v-2774c002/okWaEAQZAt0QADBJBAgiQ5PVEfBimeiBNATwlC.jpeg"
      ],
      "width": 720
    },
    "cover_medium": {
      "height": 720,
      "uri": "tos-cn-v-2774c002/okWaEAQZAt0QADBJBAgiQ5PVEfBimeiBNATwlC",
      "url_list": [
        "https://p11.douyinpic.com/aweme/200x200/tos-cn-v-2774c002/okWaEAQZAt0QADBJBAgiQ5PVEfBimeiBNATwlC.jpeg",
        "https://p26.douyinpic.com/aweme/200x200/tos-cn-v-2774c002/okWaEAQZAt0QADBJBAgiQ5PVEfBimeiBNATwlC.jpeg"
      ],
      "width": 720
    },
    "cover_thumb": {
      "height": 720,
      "uri": "tos-cn-v-2774c002/okWaEAQZAt0QADBJBAgiQ5PVEfBimeiBNATwlC",
      "url_list": [
        "https://p11.douyinpic.com/aweme/100x100/tos-cn-v-2774c002/okWaEAQZAt0QADBJBAgiQ5PVEfBimeiBNATwlC.jpeg",
        "https://p26.douyinpic.com/aweme/100x100/tos-cn-v-2774c002/okWaEAQZAt0QADBJBAgiQ5PVEfBimeiBNATwlC.jpeg"
      ],
      "width": 720
    },
    "owner_handle": "",
    "owner_id": "",
    "owner_nickname": "",
    "play_url": {
      "height": 720,
      "uri": "https://sf5-hl-cdn-tos.douyinstatic.com/obj/tos-cn-ve-2774/oQAthPF8nQD96rICoU4gfcEFmkY3Zp8BQujneB",
      "url_key": "7409559315067063066",
      "url_list": [
        "https://sf5-hl-cdn-tos.douyinstatic.com/obj/tos-cn-ve-2774/oQAthPF8nQD96rICoU4gfcEFmkY3Zp8BQujneB",
        "https://sf3-cdn-tos.douyinstatic.com/obj/tos-cn-ve-2774/oQAthPF8nQD96rICoU4gfcEFmkY3Zp8BQujneB"
      ],
      "width": 720
    },
    "title": "小孩1.3x"
  },
  "mix_info": {
    "cover_url": {
      "height": "",
      "uri": "",
      "url_list": [],
      "width": ""
    },
    "ids": "",
    "is_serial_mix": "",
    "mix_id": "",
    "mix_name": "",
    "mix_pic_type": "",
    "mix_type": "",
    "statis": {
      "current_episode": "",
      "updated_to_episode": ""
    }
  },
  "video": {
    "play_addr": {
      "uri": "",
      "url_list": []
    },
    "cover_original_scale": {
      "height": "",
      "uri": "",
      "url_list": [],
      "width": ""
    },
    "dynamic_cover": {
      "height": "",
      "uri": "",
      "url_list": [],
      "width": ""
    },
    "origin_cover": {
      "height": "",
      "uri": "",
      "url_list": [],
      "width": ""
    },
    "cover": {
      "height": "",
      "uri": "",
      "url_list": [],
      "width": ""
    }
  },
  "statistics": {
    "admire_count": 0,
    "collect_count": 7,
    "comment_count": 1,
    "digg_count": 54,
    "play_count": 0,
    "share_count": 1
  }
}